[
  {
    "id": "golden-hour",
    "title": "Sólo portraits",
    "folder": "albums/golden-hour",
    "cover": "cover.png",
    "images": [
      "01.png",
      "02.png",
      "03.png",
      "04.png"
    ]
  },
  {
    "id": "doggy",
    "title": "Nature",
    "folder": "albums/doggy",
    "cover": "cover.png",
    "images": [
      "01.png",
      "02.png",
      "03.png",
      "04.png",
      "05.png"
    ]
  },
  {
    "id": "family",
    "title": "Doggy Photoshoot",
    "folder": "albums/family",
    "cover": "cover.png",
    "images": [
      "01.png",
      "02.png"
    ]
  }
]
